flake8_pep585/__init__.py
flake8_pep585/flake_diagnostic.py
flake8_pep585/plugin.py
flake8_pep585/py.typed
flake8_pep585/rules.py
flake8_pep585-0.1.7.dist-info/entry_points.txt
flake8_pep585-0.1.7.dist-info/LICENSE
flake8_pep585-0.1.7.dist-info/WHEEL
flake8_pep585-0.1.7.dist-info/METADATA
flake8_pep585-0.1.7.dist-info/RECORD
