Metadata-Version: 2.1
Name: flake8-pep585
Version: 0.1.7
Summary: flake8 plugin to enforce new-style type hints (PEP 585)
Home-page: https://github.com/decorator-factory/flake8-pep585
License: MPL-2.0
Author: decorator-factory
Author-email: decorator-factory@yandex.ru
Requires-Python: >=3.7,<4.0
Classifier: License :: OSI Approved
Classifier: Programming Language :: Python :: 3
Classifier: Programming Language :: Python :: 3.7
Classifier: Programming Language :: Python :: 3.8
Classifier: Programming Language :: Python :: 3.9
Project-URL: Repository, https://github.com/decorator-factory/flake8-pep585
